suncompass/3_224_224_resnet_baseline_5_all.pth
suncompass/__init__.py
suncompass/add_sun_vector.py
suncompass/add_time_info.py
suncompass/analyse_balance.py
suncompass/combine_manual_labels.py
suncompass/data_loading.py
suncompass/draw_arrow.py
suncompass/extract_motion.py
suncompass/pretrained_resnet.py
suncompass/run_model_on_images.py
suncompass/suncompass.py
suncompass/video_utils.py
suncompass-0.0.1.dist-info/METADATA
suncompass-0.0.1.dist-info/WHEEL
suncompass-0.0.1.dist-info/entry_points.txt
suncompass-0.0.1.dist-info/top_level.txt
suncompass-0.0.1.dist-info/RECORD
