Metadata-Version: 2.1
Name: suncompass
Version: 0.0.1
Summary: Code for estimating the direction of the sun from a single outdoor image.
Home-page: https://github.com/hugohadfield/suncompass
Author: Hugo Hadfield
Author-email: hadfield.hugo@gmail.com
Classifier: Development Status :: 3 - Alpha
Classifier: Intended Audience :: Developers
Classifier: License :: OSI Approved :: MIT License
Classifier: Programming Language :: Python :: 3.7
Classifier: Programming Language :: Python :: 3.8
Classifier: Programming Language :: Python :: 3.9
Requires-Python: >=3.7
Requires-Dist: torch
Requires-Dist: torchvision
Requires-Dist: pandas
Requires-Dist: numpy
Requires-Dist: matplotlib
Requires-Dist: tqdm
Requires-Dist: click
Requires-Dist: Pillow
Requires-Dist: tensorboard
Requires-Dist: suncalc
